beatlesalbuns.py
beatlesalbuns-0.0.5.dist-info/METADATA
beatlesalbuns-0.0.5.dist-info/WHEEL
beatlesalbuns-0.0.5.dist-info/licenses/LICENSE.txt
beatlesalbuns-0.0.5.dist-info/RECORD
