Metadata-Version: 2.3
Name: beatlesalbuns
Version: 0.0.5
Summary: Shows a list of The Beatles albuns, stats and the band members
Author-email: Carla Godinho <carlasoniagodinho44@gmail.com>
License-File: LICENSE.txt
Classifier: License :: OSI Approved :: MIT License
Classifier: Operating System :: OS Independent
Classifier: Programming Language :: Python :: 3
Requires-Python: >=3.11
